converters/__init__.py
converters/converters.py
dataspaces_testconverters-1.0.0.dev1.dist-info/WHEEL
dataspaces_testconverters-1.0.0.dev1.dist-info/METADATA
dataspaces_testconverters-1.0.0.dev1.dist-info/RECORD
